fastapi_cli-0.0.19.dist-info/METADATA
fastapi_cli-0.0.19.dist-info/WHEEL
fastapi_cli-0.0.19.dist-info/entry_points.txt
fastapi_cli-0.0.19.dist-info/licenses/LICENSE
fastapi_cli/__init__.py
fastapi_cli/__main__.py
fastapi_cli/cli.py
fastapi_cli/config.py
fastapi_cli/discover.py
fastapi_cli/exceptions.py
fastapi_cli/logging.py
fastapi_cli/py.typed
fastapi_cli/utils/__init__.py
fastapi_cli/utils/cli.py
fastapi_cli-0.0.19.dist-info/RECORD
